nax/__init__.py
nax-0.1.0.dist-info/DESCRIPTION.rst
nax-0.1.0.dist-info/METADATA
nax-0.1.0.dist-info/RECORD
nax-0.1.0.dist-info/WHEEL
nax-0.1.0.dist-info/entry_points.txt
nax-0.1.0.dist-info/metadata.json
nax-0.1.0.dist-info/top_level.txt
