Metadata-Version: 2.0
Name: nax
Version: 0.1.0
Summary: nax name generator
Home-page: https://github.com/krisfris/nax
Author: Kris
Author-email: 31852063+krisfris@users.noreply.github.com
License: MIT
Platform: UNKNOWN
